croc/__init__.py
pycroc-0.0.1.dist-info/WHEEL
pycroc-0.0.1.dist-info/LICENSE
pycroc-0.0.1.dist-info/METADATA
pycroc-0.0.1.dist-info/RECORD
