Metadata-Version: 2.1
Name: pycroc
Version: 0.0.1
Summary: An integration testing framework written in Python :)
License: MIT
Author: Vitaman02
Author-email: filip1253@gmail.com
Requires-Python: >=3.8,<4.0
Classifier: License :: OSI Approved :: MIT License
Classifier: Programming Language :: Python :: 3
Classifier: Programming Language :: Python :: 3.8
Classifier: Programming Language :: Python :: 3.9
Classifier: Programming Language :: Python :: 3.10
Classifier: Programming Language :: Python :: 3.11
